LICENSE
MANIFEST.in
README.md
setup.py
churn_reduction_agent_based.egg-info/PKG-INFO
churn_reduction_agent_based.egg-info/SOURCES.txt
churn_reduction_agent_based.egg-info/dependency_links.txt
churn_reduction_agent_based.egg-info/entry_points.txt
churn_reduction_agent_based.egg-info/not-zip-safe
churn_reduction_agent_based.egg-info/requires.txt
churn_reduction_agent_based.egg-info/top_level.txt
d3rlpy/__init__.py
d3rlpy/_version.py
d3rlpy/argument_utility.py
d3rlpy/base.py
d3rlpy/cli.py
d3rlpy/constants.py
d3rlpy/containers.py
d3rlpy/context.py
d3rlpy/dataset.cpp
d3rlpy/dataset.pxd
d3rlpy/dataset.pyi
d3rlpy/dataset.pyx
d3rlpy/datasets.py
d3rlpy/decorators.py
d3rlpy/gpu.py
d3rlpy/itertools.py
d3rlpy/logger.py
d3rlpy/py.typed
d3rlpy/torch_utility.py
d3rlpy/algos/__init__.py
d3rlpy/algos/awac.py
d3rlpy/algos/base.py
d3rlpy/algos/bc.py
d3rlpy/algos/bcq.py
d3rlpy/algos/bear.py
d3rlpy/algos/combo.py
d3rlpy/algos/cql.py
d3rlpy/algos/crr.py
d3rlpy/algos/ddpg.py
d3rlpy/algos/dqn.py
d3rlpy/algos/iql.py
d3rlpy/algos/mopo.py
d3rlpy/algos/nfq.py
d3rlpy/algos/plas.py
d3rlpy/algos/random_policy.py
d3rlpy/algos/sac.py
d3rlpy/algos/td3.py
d3rlpy/algos/td3_plus_bc.py
d3rlpy/algos/utility.py
d3rlpy/algos/torch/__init__.py
d3rlpy/algos/torch/awac_impl.py
d3rlpy/algos/torch/base.py
d3rlpy/algos/torch/bc_impl.py
d3rlpy/algos/torch/bcq_impl.py
d3rlpy/algos/torch/bear_impl.py
d3rlpy/algos/torch/combo_impl.py
d3rlpy/algos/torch/cql_impl.py
d3rlpy/algos/torch/crr_impl.py
d3rlpy/algos/torch/ddpg_impl.py
d3rlpy/algos/torch/dqn_impl.py
d3rlpy/algos/torch/iql_impl.py
d3rlpy/algos/torch/plas_impl.py
d3rlpy/algos/torch/sac_impl.py
d3rlpy/algos/torch/td3_impl.py
d3rlpy/algos/torch/td3_plus_bc_impl.py
d3rlpy/algos/torch/utility.py
d3rlpy/cpp/include/d3rlpy/dataset.h
d3rlpy/dynamics/__init__.py
d3rlpy/dynamics/base.py
d3rlpy/dynamics/probabilistic_ensemble_dynamics.py
d3rlpy/dynamics/torch/__init__.py
d3rlpy/dynamics/torch/base.py
d3rlpy/dynamics/torch/probabilistic_ensemble_dynamics_impl.py
d3rlpy/envs/__init__.py
d3rlpy/envs/wrappers.py
d3rlpy/iterators/__init__.py
d3rlpy/iterators/base.py
d3rlpy/iterators/random_iterator.py
d3rlpy/iterators/round_iterator.py
d3rlpy/metrics/__init__.py
d3rlpy/metrics/comparer.py
d3rlpy/metrics/scorer.py
d3rlpy/models/__init__.py
d3rlpy/models/builders.py
d3rlpy/models/encoders.py
d3rlpy/models/optimizers.py
